{
  "name": "chauffeur",
  "base": "PersistedModel",
  "idInjection": true,
  "options": {
    "validateUpsert": true
  },
  "properties": {
    "Nom": {
      "type": "string",
      "required": true
    },
    "prenom": {
      "type": "string",
      "required": true
    },
    "email": {
      "type": "string",
      "required": true
    },
    "password": {
      "type": "string",
      "required": true
    }
  },
  "validations": [],
  "relations": {},
  "acls": [
    {
      "accessType": "*",
      "principalType": "ROLE",
      "principalId": "$unauthenticated",
      "permission": "DENY"
    }
  ],
  "methods": {}
}
